google/ads/datamanager/__init__.py
google/ads/datamanager/gapic_version.py
google/ads/datamanager/py.typed
google/ads/datamanager_v1/__init__.py
google/ads/datamanager_v1/gapic_metadata.json
google/ads/datamanager_v1/gapic_version.py
google/ads/datamanager_v1/py.typed
google/ads/datamanager_v1/services/__init__.py
google/ads/datamanager_v1/services/ingestion_service/__init__.py
google/ads/datamanager_v1/services/ingestion_service/async_client.py
google/ads/datamanager_v1/services/ingestion_service/client.py
google/ads/datamanager_v1/services/ingestion_service/transports/__init__.py
google/ads/datamanager_v1/services/ingestion_service/transports/base.py
google/ads/datamanager_v1/services/ingestion_service/transports/grpc.py
google/ads/datamanager_v1/services/ingestion_service/transports/grpc_asyncio.py
google/ads/datamanager_v1/services/ingestion_service/transports/rest.py
google/ads/datamanager_v1/services/ingestion_service/transports/rest_base.py
google/ads/datamanager_v1/types/__init__.py
google/ads/datamanager_v1/types/audience.py
google/ads/datamanager_v1/types/cart_data.py
google/ads/datamanager_v1/types/consent.py
google/ads/datamanager_v1/types/destination.py
google/ads/datamanager_v1/types/device_info.py
google/ads/datamanager_v1/types/encryption_info.py
google/ads/datamanager_v1/types/error.py
google/ads/datamanager_v1/types/event.py
google/ads/datamanager_v1/types/experimental_field.py
google/ads/datamanager_v1/types/ingestion_service.py
google/ads/datamanager_v1/types/item_parameter.py
google/ads/datamanager_v1/types/match_rate.py
google/ads/datamanager_v1/types/processing_errors.py
google/ads/datamanager_v1/types/request_status_per_destination.py
google/ads/datamanager_v1/types/terms_of_service.py
google/ads/datamanager_v1/types/user_data.py
google/ads/datamanager_v1/types/user_properties.py
google_ads_datamanager-0.3.0.dist-info/licenses/LICENSE
google_ads_datamanager-0.3.0.dist-info/METADATA
google_ads_datamanager-0.3.0.dist-info/WHEEL
google_ads_datamanager-0.3.0.dist-info/top_level.txt
google_ads_datamanager-0.3.0.dist-info/RECORD
